functions26/Data2D.py
functions26/DataAutoPLE.py
functions26/DataDictXXX.py
functions26/DataFrame26.py
functions26/DataImage.py
functions26/DataImportXYZ.py
functions26/DataMultiXXX.py
functions26/DataXXX.py
functions26/Dict26.py
functions26/FileManipulation.py
functions26/FilenameManager.py
functions26/FittingManager.py
functions26/InstrumentHandler.py
functions26/LiveUpdate.py
functions26/PL_Lines.py
functions26/Peak_Analysis.py
functions26/Plot2D.py
functions26/__init__.py
functions26/constants.py
functions26/unit_conversions.py
functions26/useful_functions.py
functions26/external_data/__init__.py
functions26/external_data/refractive_index_air.csv
functions26/filing/QDLFiling.py
functions26/filing/__init__.py
functions26/instruments/DataGenerators.py
functions26/instruments/RFSynthesizers.py
functions26/instruments/__init__.py
functions26/instruments/powermeter.py
functions26/instruments/spcm.py
functions26/units/UnitClass.py
functions26/units/__init__.py
functions26/units/angle.py
functions26/units/area.py
functions26/units/energy.py
functions26/units/frequency.py
functions26/units/length.py
functions26/units/magnetic_field.py
functions26/units/power.py
functions26/units/temperature.py
functions26/units/time.py
functions26/units/volume.py
functions26-0.1.4.1.dist-info/LICENSE
functions26-0.1.4.1.dist-info/METADATA
functions26-0.1.4.1.dist-info/WHEEL
functions26-0.1.4.1.dist-info/top_level.txt
functions26-0.1.4.1.dist-info/RECORD
