Metadata-Version: 2.1
Name: functions26
Version: 0.1.4.1
Summary: Supporting functions for Fu lab 26 room
Home-page: https://github.com/vasilisniaouris/functions26
Author: Vasilis Niaouris
Author-email: vasilisniaouris@gmail.com
License: UNKNOWN
Platform: UNKNOWN
Classifier: Programming Language :: Python :: 3
Classifier: License :: OSI Approved :: MIT License
Classifier: Operating System :: OS Independent
Requires-Python: >=3.8
License-File: LICENSE
Requires-Dist: collections-extended
Requires-Dist: lmfit
Requires-Dist: matplotlib
Requires-Dist: nidaqmx
Requires-Dist: numpy
Requires-Dist: pandas
Requires-Dist: py3-validate-email
Requires-Dist: py3dns
Requires-Dist: pydaqmx
Requires-Dist: pyserial
Requires-Dist: pyvisa
Requires-Dist: pyqt5
Requires-Dist: pyqtgraph
Requires-Dist: scipy
Requires-Dist: seaborn
Requires-Dist: spinmob
Requires-Dist: windfreak
